odoo/addons/currency_rate_update_xe/README.rst
odoo/addons/currency_rate_update_xe/__init__.py
odoo/addons/currency_rate_update_xe/__manifest__.py
odoo/addons/currency_rate_update_xe/i18n/currency_rate_update_xe.pot
odoo/addons/currency_rate_update_xe/models/__init__.py
odoo/addons/currency_rate_update_xe/models/res_company.py
odoo/addons/currency_rate_update_xe/models/res_config_settings.py
odoo/addons/currency_rate_update_xe/models/res_currency_rate_provider_XE.py
odoo/addons/currency_rate_update_xe/readme/CONFIGURE.rst
odoo/addons/currency_rate_update_xe/readme/CONTRIBUTORS.rst
odoo/addons/currency_rate_update_xe/readme/DESCRIPTION.rst
odoo/addons/currency_rate_update_xe/static/description/icon.png
odoo/addons/currency_rate_update_xe/static/description/index.html
odoo/addons/currency_rate_update_xe/tests/__init__.py
odoo/addons/currency_rate_update_xe/tests/test_currency_rate_update_xe.py
odoo/addons/currency_rate_update_xe/views/res_config_settings.xml
odoo12_addon_currency_rate_update_xe-12.0.1.0.0.99.dev7.dist-info/METADATA
odoo12_addon_currency_rate_update_xe-12.0.1.0.0.99.dev7.dist-info/WHEEL
odoo12_addon_currency_rate_update_xe-12.0.1.0.0.99.dev7.dist-info/top_level.txt
odoo12_addon_currency_rate_update_xe-12.0.1.0.0.99.dev7.dist-info/RECORD
